Metadata-Version: 1.0
Name: phonetizer-google
Version: 0.9
Summary: Just fetch the phoneme from Google Translate, for educational purpose only
Home-page: https://github.com/maifeeulasad/phonetizer-google
Author: Maifee Ul Asad
Author-email: maifeeulasad@gmail.com
License: MIT
Platform: UNKNOWN
